pypixyz/__init__.py
pypixyz/main.py
pypixyz-0.1.0.dist-info/entry_points.txt
pypixyz-0.1.0.dist-info/METADATA
pypixyz-0.1.0.dist-info/WHEEL
pypixyz-0.1.0.dist-info/RECORD
